desktop_file_generate/__init__.py
desktop_file_generate/__main__.py
desktop_file_generate/desktop_file_generate.py
desktop_file_generate-1.0.1.dist-info/LICENSE
desktop_file_generate-1.0.1.dist-info/METADATA
desktop_file_generate-1.0.1.dist-info/WHEEL
desktop_file_generate-1.0.1.dist-info/entry_points.txt
desktop_file_generate-1.0.1.dist-info/top_level.txt
desktop_file_generate-1.0.1.dist-info/RECORD
