Metadata-Version: 2.1
Name: desktop-file-generate
Version: 1.0.1
Summary: 生成.desktop文件
Home-page: https://github.com/fncong
Author: fncong
Author-email: fncong@outlook.com
License: UNKNOWN
Platform: UNKNOWN
